setup.py
SystemAutopsy.egg-info/PKG-INFO
SystemAutopsy.egg-info/SOURCES.txt
SystemAutopsy.egg-info/dependency_links.txt
SystemAutopsy.egg-info/entry_points.txt
SystemAutopsy.egg-info/top_level.txt
system_autopsy/__init__.py
system_autopsy/default_components.py
system_autopsy/utils.py