Metadata-Version: 1.0
Name: SystemAutopsy
Version: 0.1
Summary: Extensible tool to take a snapshot of important things a system is doing while you're firefighting
Home-page: UNKNOWN
Author: Rory McCann
Author-email: rory@technomancy.org
License: GPLv3+
Platform: UNKNOWN
